earthcraft_countries_api/__init__.py
earthcraft_countries_api/__main__.py
earthcraft_countries_api/earthcraft_countries_api.py
earthcraft_countries_api/json/dicts/country_name_to_iso3.json
earthcraft_countries_api/json/dicts/iso2_to_iso3.json
earthcraft_countries_api/json/dicts/iso3_to_borders.json
earthcraft_countries_api/json/dicts/iso3_to_calling_code.json
earthcraft_countries_api/json/dicts/iso3_to_capital.json
earthcraft_countries_api/json/dicts/iso3_to_full_name.json
earthcraft_countries_api/json/dicts/iso3_to_iso2.json
earthcraft_countries_api/json/dicts/iso3_to_languages.json
earthcraft_countries_api/json/dicts/iso3_to_name.json
earthcraft_countries_api/json/dicts/iso3_to_population.json
earthcraft_countries_api/json/dicts/iso3_to_un_gdp_nominal.json
earthcraft_countries_api/json/dicts/official_country_names.json
earthcraft_countries_api/json/lists/countries_iso2_list.json
earthcraft_countries_api/json/lists/countries_iso3_list.json
earthcraft_countries_api/json/lists/countries_name_list.json
earthcraft_countries_api-1.0.2.dist-info/LICENSE.txt
earthcraft_countries_api-1.0.2.dist-info/METADATA
earthcraft_countries_api-1.0.2.dist-info/WHEEL
earthcraft_countries_api-1.0.2.dist-info/top_level.txt
earthcraft_countries_api-1.0.2.dist-info/RECORD
