Metadata-Version: 2.1
Name: earthcraft-countries-api
Version: 1.0.2
Summary: Countries API used by the EarthCraft bot
Home-page: https://earthcraftmc.net/
Author: FrenchFries8854
Author-email: frenchfries8854@gmail.com
License: MIT
Platform: UNKNOWN
Classifier: License :: OSI Approved :: MIT License
Classifier: Programming Language :: Python :: 3
Classifier: Programming Language :: Python :: 3.9
License-File: LICENSE.txt
Requires-Dist: feedparser
Requires-Dist: html2text
